{
  "id": "wfrp2e",
  "title": "Warhammer Fantasy RPG 2",
  "description": "The Warhammer Fantasy RPG 2 system for FoundryVTT!",
  "authors": [
    {
      "name": "Asacolips",
      "discord": "asacolips"
    },
    {
      "name": "Lee Talman",
      "discord": ".pizzaWizard"
    },
    {
      "name": "Sylvan33",
      "discord": "sylvan33"
    }
  ],
  "url": "https://github.com/Sylvan333/wfrp2e/",
  "license": "LICENSE.txt",
  "readme": "README.md",
  "bugs": "Replace this with a link to file issues or tickets",
  "changelog": "CHANGELOG.md",
  "media": [
    {
      "type": "setup",
      "url": "systems/wfrp2e/assets/anvil-impact.png",
      "thumbnail": "systems/wfrp2e/assets/anvil-impact.png"
    }
  ],
  "version": "0.0.1",
  "compatibility": {
    "minimum": 11,
    "verified": "11.315"
  },
  "esmodules": ["module/wfrp2e.mjs"],
  "styles": ["css/wfrp2e.css"],
  "languages": [
    {
      "lang": "en",
      "name": "English",
      "path": "lang/en.json"
    }
  ],
  "packs": [],
  "packFolders": [],
  "socket": false,
  "manifest": "https://github.com/Sylvan333/wfrp2e/releases/latest/download/system.json",
  "download": "https://github.com/Sylvan333/wfrp2e/releases/download/0.0.1/wfrp2e.zip",
  "background": "systems/wfrp2e/assets/anvil-impact.png",
  "gridDistance": 2,
  "gridUnits": "m",
  "primaryTokenAttribute": "health",
  "secondaryTokenAttribute": "ammo"
}
